LICENSE
README.md
setup.py
bin/uhepp
uhepp/__init__.py
uhepp/utils.py
uhepp.egg-info/PKG-INFO
uhepp.egg-info/SOURCES.txt
uhepp.egg-info/dependency_links.txt
uhepp.egg-info/requires.txt
uhepp.egg-info/top_level.txt
uhepp/tests/__init__.py
uhepp/tests/test_from.py
uhepp/tests/test_graph.py
uhepp/tests/test_line.py
uhepp/tests/test_numpy.py
uhepp/tests/test_outside.py
uhepp/tests/test_plotting.py
uhepp/tests/test_ratioitem.py
uhepp/tests/test_saveload.py
uhepp/tests/test_smartdict.py
uhepp/tests/test_stack.py
uhepp/tests/test_stackitem.py
uhepp/tests/test_uncertainty.py
uhepp/tests/test_utils.py
uhepp/tests/test_yield.py