Metadata-Version: 2.1
Name: uhepp
Version: 0.2.0
Summary: Universal HEP plots
Home-page: https://gitlab.cern.ch/fsauerbu/uhepp
Author: Frank Sauerburger
Author-email: f.sauerburger@cern.ch
License: MIT
Platform: UNKNOWN
Classifier: Intended Audience :: Science/Research
Classifier: License :: OSI Approved :: MIT License
Classifier: Programming Language :: Python :: 3 :: Only
Classifier: Topic :: Scientific/Engineering :: Physics
License-File: LICENSE
